pytoolbase/__init__.py
pytoolbase/config.py
pytoolbase/exceptions.py
pytoolbase/filemgr.py
pytoolbase/retry.py
pytoolbase/synchronize.py
pytoolbase-1.0.2.dist-info/LICENSE.txt
pytoolbase-1.0.2.dist-info/METADATA
pytoolbase-1.0.2.dist-info/WHEEL
pytoolbase-1.0.2.dist-info/RECORD
